joattcountry7/__init__.py
joattcountry7/joatcountry7.py
joatcountry7-0.0.1.dist-info/LICENSE
joatcountry7-0.0.1.dist-info/METADATA
joatcountry7-0.0.1.dist-info/WHEEL
joatcountry7-0.0.1.dist-info/top_level.txt
joatcountry7-0.0.1.dist-info/RECORD
