Metadata-Version: 2.1
Name: joatcountry7
Version: 0.0.1
Summary: Negara Informasi Inform Negara negara 
Home-page: https://github.com/syahrulcaem/joatcountry7
Author: scaem007
Author-email: <syahrulromadhonmuhamamd@gmail.com>
License: MIT
Keywords: country,negara
Classifier: Development Status :: 1 - Planning
License-File: LICENSE
